{
    "nodes": [
        {
            "Tweet": "Deputy",
            "UserName": "\u03a4\u03a3\u0391\u039a\u0391\u039b\u03a9\u03a4\u039f\u03a3",
            "Date": "null",
            "icon": "http:\/\/www.newmoney.gr\/media\/k2\/items\/cache\/f5aee5f4148adfff00fdebdedc794929_XL.jpg?t=1422826027",
            "BelongsTo": "null",
            "size": "big",
            "name": "basic-graph"
        },
        {
            "Tweet": "\u039d\u0395\u039f\u039b\u0395\u03a1\u0391 http:\/\/t.co\/Cdyq7iBwsg",
            "UserName": "neolera",
            "Date": "Fri May 29 14:50:02 +0000 2015",
            "icon": "http:\/\/pbs.twimg.com\/profile_images\/1445846065\/avatar_normal.jpg",
            "BelongsTo": "\u03a4\u03a3\u0391\u039a\u0391\u039b\u03a9\u03a4\u039f\u03a3",
            "size": "small",
            "name": "basic-graph"
        },
        {
            "Tweet": "\u039d\u0395\u039f\u039b\u0395\u03a1\u0391 http:\/\/t.co\/flQ92O1aCj",
            "UserName": "neolera",
            "Date": "Fri May 29 14:50:01 +0000 2015",
            "icon": "http:\/\/pbs.twimg.com\/profile_images\/1445846065\/avatar_normal.jpg",
            "BelongsTo": "\u03a4\u03a3\u0391\u039a\u0391\u039b\u03a9\u03a4\u039f\u03a3",
            "size": "small",
            "name": "basic-graph"
        },
        {
            "Tweet": "\u0395\u03c5. \u03a4\u03c3\u03b1\u03ba\u03b1\u03bb\u03ce\u03c4\u03bf\u03c2 \u03c3\u03c4\u03b7\u03bd \u00ab\u0391\u03b3\u03bf\u03c1\u03ac\u00bb: \u00ab\u03a3\u03c5\u03bc\u03c6\u03c9\u03bd\u03af\u03b1 \u03bd\u03b1 '\u03bd\u03b1\u03b9 \u03ba\u03b9 \u03cc,\u03c4\u03b9 \u03bd\u03b1 '\u03bd\u03b1\u03b9\u00bb \u03b5\u03bc\u03b5\u03af\u03c2 \u03b4\u03b5\u03bd \u03b8\u03b1 \u03c5\u03c0\u03bf\u03b3\u03c1\u03ac\u03c8\u03bf\u03c5\u03bc\u03b5 https:\/\/t.co\/TYTrXEsjYs via @sharethis",
            "UserName": "Dimitris Tsekeris",
            "Date": "Fri May 29 14:18:44 +0000 2015",
            "icon": "http:\/\/pbs.twimg.com\/profile_images\/505062254455562240\/l3yyCPxr_normal.jpeg",
            "BelongsTo": "\u03a4\u03a3\u0391\u039a\u0391\u039b\u03a9\u03a4\u039f\u03a3",
            "size": "small",
            "name": "basic-graph"
        },
        {
            "Tweet": "\u0386\u03bd\u03c4\u03b5, \u03b2\u03c1\u03b5 \u0395\u03c5\u03ba\u03bb\u03b5\u03af\u03b4\u03b7 \u03bc\u03b5 \u03c4\u03b1 \u03ba\u03af\u03c4\u03c1\u03b9\u03bd\u03b1! http:\/\/t.co\/54Soa5ruJ5",
            "UserName": "Irm@",
            "Date": "Fri May 29 13:54:31 +0000 2015",
            "icon": "http:\/\/pbs.twimg.com\/profile_images\/1832147265\/MARY_POPPINS_normal.jpg",
            "BelongsTo": "\u03a4\u03a3\u0391\u039a\u0391\u039b\u03a9\u03a4\u039f\u03a3",
            "size": "small",
            "name": "basic-graph"
        },
        {
            "Tweet": "\u0395\u03c5. \u03a4\u03c3\u03b1\u03ba\u03b1\u03bb\u03ce\u03c4\u03bf\u03c2 \u03c3\u03c4\u03b7\u03bd \u00ab\u0391\u03b3\u03bf\u03c1\u03ac\u00bb: \u00ab\u03a3\u03c5\u03bc\u03c6\u03c9\u03bd\u03af\u03b1 \u03bd\u03b1 '\u03bd\u03b1\u03b9 \u03ba\u03b9 \u03cc,\u03c4\u03b9 \u03bd\u03b1 '\u03bd\u03b1\u03b9\u00bb \u03b5\u03bc\u03b5\u03af\u03c2 \u03b4\u03b5\u03bd \u03b8\u03b1 \u03c5\u03c0\u03bf\u03b3\u03c1\u03ac\u03c8\u03bf\u03c5\u03bc\u03b5 https:\/\/t.co\/GLW5t8sHN6 via @sharethis",
            "UserName": "Dimitris Tsekeris",
            "Date": "Fri May 29 12:47:57 +0000 2015",
            "icon": "http:\/\/pbs.twimg.com\/profile_images\/505062254455562240\/l3yyCPxr_normal.jpeg",
            "BelongsTo": "\u03a4\u03a3\u0391\u039a\u0391\u039b\u03a9\u03a4\u039f\u03a3",
            "size": "small",
            "name": "basic-graph"
        },
        {
            "Tweet": "#\u03a4\u03c3\u03b1\u03ba\u03b1\u03bb\u03ce\u03c4\u03bf\u03c2 \u03c3\u03c4\u03b7\u03bd \u0391\u03b3\u03bf\u03c1\u03ac: \u0393\u03b9\u03b1 \u03bc\u03b1\u03c2 \u03b7 \u03c1\u03ae\u03be\u03b7 \u03b4\u03b5\u03bd \u03b5\u03af\u03bd\u03b1\u03b9 \u03c6\u03b5\u03c4\u03af\u03c7 http:\/\/t.co\/S226ah04I2",
            "UserName": "THE CITIZEN",
            "Date": "Fri May 29 12:12:52 +0000 2015",
            "icon": "http:\/\/pbs.twimg.com\/profile_images\/568916020908154880\/Mnbjdwmf_normal.png",
            "BelongsTo": "\u03a4\u03a3\u0391\u039a\u0391\u039b\u03a9\u03a4\u039f\u03a3",
            "size": "small",
            "name": "basic-graph"
        },
        {
            "Tweet": "\u03a4\u03c3\u03b1\u03ba\u03b1\u03bb\u03ce\u03c4\u03bf\u03c2: \u03a3\u03c5\u03bc\u03c6\u03c9\u03bd\u03af\u03b1 \u03cc,\u03c4\u03b9 \u03bd\u03b1 '\u03bd\u03b1\u03b9 \u03b4\u03b5\u03bd \u03c5\u03c0\u03bf\u03b3\u03c1\u03ac\u03c6\u03bf\u03c5\u03bc\u03b5 - TVXS - TV \u03a7\u03c9\u03c1\u03af\u03c2\u2026 http:\/\/t.co\/WbbC8LarRk | http:\/\/t.co\/lyLVQkxWms #news",
            "UserName": "Newstalk",
            "Date": "Fri May 29 12:08:17 +0000 2015",
            "icon": "http:\/\/pbs.twimg.com\/profile_images\/3383970022\/3f15fff8fd58823c14b6241cb645fd42_normal.jpeg",
            "BelongsTo": "\u03a4\u03a3\u0391\u039a\u0391\u039b\u03a9\u03a4\u039f\u03a3",
            "size": "small",
            "name": "basic-graph"
        },
        {
            "Tweet": "\u03a4\u03c3\u03b1\u03ba\u03b1\u03bb\u03ce\u03c4\u03bf\u03c2: \u0394\u03bf\u03c5\u03bb\u03b5\u03cd\u03bf\u03c5\u03bc\u03b5 \u03b3\u03b9\u03b1 \u03ba\u03b1\u03bb\u03ae \u03c3\u03c5\u03bc\u03c6\u03c9\u03bd\u03af\u03b1, \u03b1\u03bb\u03bb\u03ac \u03b7 \u03c1\u03ae\u03be\u03b7 \u03b4\u03b5\u03bd \u03b5\u03af\u03bd\u03b1\u03b9 \u03c6\u03b5\u03c4\u03af\u03c7 | altsantiri.gr http:\/\/t.co\/DZRkN2SBbS",
            "UserName": "\u0397\u03bb\u03ad\u03ba\u03c4\u03c1\u03b1 \u0393\u03b1\u03bb\u03b1\u03bd\u03bf\u03cd",
            "Date": "Fri May 29 11:55:56 +0000 2015",
            "icon": "http:\/\/pbs.twimg.com\/profile_images\/576819036119441408\/LJ7O-BMk_normal.jpeg",
            "BelongsTo": "\u03a4\u03a3\u0391\u039a\u0391\u039b\u03a9\u03a4\u039f\u03a3",
            "size": "small",
            "name": "basic-graph"
        },
        {
            "Tweet": "\u03a4\u03c3\u03b1\u03ba\u03b1\u03bb\u03ce\u03c4\u03bf\u03c2: \u0397 \u03c1\u03ae\u03be\u03b7 \u03b4\u03b5\u03bd \u03b5\u03af\u03bd\u03b1\u03b9\u2026 \u03c6\u03b5\u03c4\u03af\u03c7! http:\/\/t.co\/CEyxPvYJqY",
            "UserName": "\u03a4\u03bf \u03a0\u03b1\u03c1\u03b1\u03c3\u03ba\u03ae\u03bd\u03b9\u03bf",
            "Date": "Fri May 29 11:44:03 +0000 2015",
            "icon": "http:\/\/pbs.twimg.com\/profile_images\/2293415199\/zwk5yc8lvbqoyxx6swd5_normal.png",
            "BelongsTo": "\u03a4\u03a3\u0391\u039a\u0391\u039b\u03a9\u03a4\u039f\u03a3",
            "size": "small",
            "name": "basic-graph"
        },
        {
            "Tweet": "\u03a4\u03c3\u03b1\u03ba\u03b1\u03bb\u03ce\u03c4\u03bf\u03c2: \u03a4\u03b1 \u03cc\u03c1\u03b9\u03b1 \u03bc\u03b1\u03c2 \u03b5\u03af\u03bd\u03b1\u03b9 \u03c0\u03bf\u03bb\u03cd \u03c3\u03c5\u03b3\u03ba\u03b5\u03ba\u03c1\u03b9\u03bc\u03ad\u03bd\u03b1\nhttp:\/\/t.co\/fK8sI6C1F5",
            "UserName": "Nooz.gr",
            "Date": "Fri May 29 11:28:50 +0000 2015",
            "icon": "http:\/\/pbs.twimg.com\/profile_images\/3498150024\/fcc335c41d515bbc016ae8ffe80d816f_normal.jpeg",
            "BelongsTo": "\u03a4\u03a3\u0391\u039a\u0391\u039b\u03a9\u03a4\u039f\u03a3",
            "size": "small",
            "name": "basic-graph"
        },
        {
            "Tweet": "\u039d\u0395\u039f\u039b\u0395\u03a1\u0391 http:\/\/t.co\/dDlUYdkpGb",
            "UserName": "neolera",
            "Date": "Fri May 29 11:23:44 +0000 2015",
            "icon": "http:\/\/pbs.twimg.com\/profile_images\/1445846065\/avatar_normal.jpg",
            "BelongsTo": "\u03a4\u03a3\u0391\u039a\u0391\u039b\u03a9\u03a4\u039f\u03a3",
            "size": "small",
            "name": "basic-graph"
        },
        {
            "Tweet": "@AnastasiadesCY \u03a0\u03c1\u03cc\u03b5\u03b4\u03c1\u03b5 \u03c7\u03b1\u03b9\u03c1\u03b5\u03c4\u03b9\u03c3\u03bc\u03bf\u03cd\u03c2 \u03b1\u03c0\u03cc \u03c4\u03bf\u03bd \u0395\u03c5\u03ba\u03bb\u03b5\u03af\u03b4\u03b7 @tsakalotos. \n\u0395\u03af\u03c0\u03b5 \u03cc\u03c4\u03b9 \u03b5\u03af\u03c3\u03b1\u03b9 \u03c0\u03c1\u03bf\u03b2\u03bb\u03ad\u03c8\u03b9\u03bc\u03bf\u03c2 \u03b3\u03b9\u03b1 \u03c4\u03b7\u03bd \u03c4\u03c1\u03cc\u03b9\u03ba\u03b1 \u03cc\u03c0\u03c9\u03c2 \u03bf @samaras_antonis\n#cyxy",
            "UserName": "Kokomos",
            "Date": "Fri May 29 11:20:25 +0000 2015",
            "icon": "http:\/\/pbs.twimg.com\/profile_images\/592469787701219328\/OwtY81ti_normal.jpg",
            "BelongsTo": "\u03a4\u03a3\u0391\u039a\u0391\u039b\u03a9\u03a4\u039f\u03a3",
            "size": "small",
            "name": "basic-graph"
        },
        {
            "Tweet": "RT @tvxs: \u03a4\u03c3\u03b1\u03ba\u03b1\u03bb\u03ce\u03c4\u03bf\u03c2: \u03a3\u03c5\u03bc\u03c6\u03c9\u03bd\u03af\u03b1 \u03cc,\u03c4\u03b9 \u03bd\u03b1 \u2018\u03bd\u03b1\u03b9 \u03b4\u03b5\u03bd \u03c5\u03c0\u03bf\u03b3\u03c1\u03ac\u03c6\u03bf\u03c5\u03bc\u03b5  http:\/\/t.co\/E78OcSrXya",
            "UserName": "Dimitri Deliolanes",
            "Date": "Fri May 29 11:12:26 +0000 2015",
            "icon": "http:\/\/pbs.twimg.com\/profile_images\/592603495649419264\/jbsxjK4l_normal.jpg",
            "BelongsTo": "\u03a4\u03a3\u0391\u039a\u0391\u039b\u03a9\u03a4\u039f\u03a3",
            "size": "small",
            "name": "basic-graph"
        },
        {
            "Tweet": "#tsakalotos '\u03b4\u03b5\u03bd \u03b5\u03af\u03bc\u03b1\u03c3\u03c4\u03b5 \u03c0\u03c1\u03bf\u03b2\u03bb\u03ad\u03c8\u03b9\u03bc\u03bf\u03b9 \u03b3\u03b9\u03b1 \u03c4\u03bf\u03c5\u03c2 \u03b4\u03b1\u03bd\u03b5\u03b9\u03c3\u03c4\u03ad\u03c2 \u03bc\u03b1\u03c2'! - \u03b8\u03b1\u03bd\u03b1\u03c4\u03b5\u03c1\u03cc \u03c7\u03b9\u03bf\u03cd\u03bc\u03bf\u03c1! #Grexit",
            "UserName": "Metanastis Liastos",
            "Date": "Fri May 29 11:08:45 +0000 2015",
            "icon": "http:\/\/pbs.twimg.com\/profile_images\/566981366860877824\/Z9N8agkS_normal.jpeg",
            "BelongsTo": "\u03a4\u03a3\u0391\u039a\u0391\u039b\u03a9\u03a4\u039f\u03a3",
            "size": "small",
            "name": "basic-graph"
        },
        {
            "Tweet": "RT @sanloukas410: \u03a4\u03c3\u03b1\u03ba\u03b1\u03bb\u03ce\u03c4\u03bf\u03c2: \u0393\u03b9\u03b1 \u03b5\u03bc\u03ac\u03c2 \u03b7 \u03c1\u03ae\u03be\u03b7 \u03b4\u03b5\u03bd \u03b5\u03af\u03bd\u03b1\u03b9 \u03c6\u03b5\u03c4\u03af\u03c7 http:\/\/t.co\/CXXJrmERKW",
            "UserName": "THIVAHELLAS",
            "Date": "Fri May 29 10:59:10 +0000 2015",
            "icon": "http:\/\/pbs.twimg.com\/profile_images\/562348519197908992\/6EGz0L2c_normal.jpeg",
            "BelongsTo": "\u03a4\u03a3\u0391\u039a\u0391\u039b\u03a9\u03a4\u039f\u03a3",
            "size": "small",
            "name": "basic-graph"
        },
        {
            "Tweet": "\u03a4\u03c3\u03b1\u03ba\u03b1\u03bb\u03ce\u03c4\u03bf\u03c2: \u0393\u03b9\u03b1 \u03b5\u03bc\u03ac\u03c2 \u03b7 \u03c1\u03ae\u03be\u03b7 \u03b4\u03b5\u03bd \u03b5\u03af\u03bd\u03b1\u03b9 \u03c6\u03b5\u03c4\u03af\u03c7 http:\/\/t.co\/CXXJrmERKW",
            "UserName": "\u039d\u03b9\u03ba\u03bf\u03c2 \u0393\u03b5\u03bd\u03b5\u03ba\u03b1\u03c1\u03b7\u03c2",
            "Date": "Fri May 29 10:37:53 +0000 2015",
            "icon": "http:\/\/pbs.twimg.com\/profile_images\/585308072853241856\/_pXAt8TH_normal.jpg",
            "BelongsTo": "\u03a4\u03a3\u0391\u039a\u0391\u039b\u03a9\u03a4\u039f\u03a3",
            "size": "small",
            "name": "basic-graph"
        },
        {
            "Tweet": "\u03a4\u03c3\u03b1\u03ba\u03b1\u03bb\u03ce\u03c4\u03bf\u03c2: \u0393\u03b9\u03b1 \u03b5\u03bc\u03ac\u03c2 \u03b7 \u03c1\u03ae\u03be\u03b7 \u03b4\u03b5\u03bd \u03b5\u03af\u03bd\u03b1\u03b9 \u03c6\u03b5\u03c4\u03af\u03c7 http:\/\/t.co\/s4hoARXukz",
            "UserName": "nocomments.gr",
            "Date": "Fri May 29 10:21:19 +0000 2015",
            "icon": "http:\/\/pbs.twimg.com\/profile_images\/2762496993\/6f579a562bf1ab0b59569b416aa9561b_normal.png",
            "BelongsTo": "\u03a4\u03a3\u0391\u039a\u0391\u039b\u03a9\u03a4\u039f\u03a3",
            "size": "small",
            "name": "basic-graph"
        },
        {
            "Tweet": "\u03a4\u03c3\u03b1\u03ba\u03b1\u03bb\u03ce\u03c4\u03bf\u03c2: \u0397 \u03c1\u03ae\u03be\u03b7 \u03b4\u03b5\u03bd \u03b5\u03af\u03bd\u03b1\u03b9\u2026 \u03c6\u03b5\u03c4\u03af\u03c7! http:\/\/t.co\/fsYR7EIVbV",
            "UserName": "Dimitris Leonov",
            "Date": "Fri May 29 10:10:10 +0000 2015",
            "icon": "http:\/\/pbs.twimg.com\/profile_images\/1599465638\/che_2_normal.jpg",
            "BelongsTo": "\u03a4\u03a3\u0391\u039a\u0391\u039b\u03a9\u03a4\u039f\u03a3",
            "size": "small",
            "name": "basic-graph"
        },
        {
            "Tweet": "RT @leftgr: \u0395. \u03a4\u03c3\u03b1\u03ba\u03b1\u03bb\u03ce\u03c4\u03bf\u03c2 \u03c3\u03c4\u03b7\u03bd \u00ab\u0391\u03b3\u03bf\u03c1\u03ac\u00bb: \"\u03a3\u03c5\u03bc\u03c6\u03c9\u03bd\u03af\u03b1 \u03bd\u03b1 \u03bd\u03b1\u03b9, \u03ba\u03b1\u03b9 \u03cc,\u03c4\u03b9 \u03bd\u03b1 \u03bd\u03b1\u03b9\" \u03b5\u03bc\u03b5\u03af\u03c2 \u03b4\u03b5\u03bd \u03b8\u03b1 \u03c5\u03c0\u03bf\u03b3\u03c1\u03ac\u03c8\u03bf\u03c5\u03bc\u03b5 :: left.gr http:\/\/t.co\/xZtyItA6CV",
            "UserName": "d.aliferopoulos",
            "Date": "Fri May 29 10:00:50 +0000 2015",
            "icon": "http:\/\/pbs.twimg.com\/profile_images\/378800000481707864\/a5996cb7ae728f423f3933f85b14895e_normal.jpeg",
            "BelongsTo": "\u03a4\u03a3\u0391\u039a\u0391\u039b\u03a9\u03a4\u039f\u03a3",
            "size": "small",
            "name": "basic-graph"
        },
        {
            "Tweet": "RT @paraskhnio: \u03a4\u03c3\u03b1\u03ba\u03b1\u03bb\u03ce\u03c4\u03bf\u03c2: \u0397 \u03c1\u03ae\u03be\u03b7 \u03b4\u03b5\u03bd \u03b5\u03af\u03bd\u03b1\u03b9\u2026 \u03c6\u03b5\u03c4\u03af\u03c7! http:\/\/t.co\/CEyxPvYJqY http:\/\/t.co\/SL0u2H6Qcx",
            "UserName": "karfitsa.gr",
            "Date": "Fri May 29 09:46:29 +0000 2015",
            "icon": "http:\/\/pbs.twimg.com\/profile_images\/378800000339753613\/75c4f77ba3a7120f9f08c8c02e421620_normal.png",
            "BelongsTo": "\u03a4\u03a3\u0391\u039a\u0391\u039b\u03a9\u03a4\u039f\u03a3",
            "size": "small",
            "name": "basic-graph"
        }
    ],
    "links": [
        {
            "source": 1,
            "target": 0
        },
        {
            "source": 2,
            "target": 0
        },
        {
            "source": 3,
            "target": 0
        },
        {
            "source": 4,
            "target": 0
        },
        {
            "source": 5,
            "target": 0
        },
        {
            "source": 6,
            "target": 0
        },
        {
            "source": 7,
            "target": 0
        },
        {
            "source": 8,
            "target": 0
        },
        {
            "source": 9,
            "target": 0
        },
        {
            "source": 10,
            "target": 0
        },
        {
            "source": 11,
            "target": 0
        },
        {
            "source": 12,
            "target": 0
        },
        {
            "source": 13,
            "target": 0
        },
        {
            "source": 14,
            "target": 0
        },
        {
            "source": 15,
            "target": 0
        },
        {
            "source": 16,
            "target": 0
        },
        {
            "source": 17,
            "target": 0
        },
        {
            "source": 18,
            "target": 0
        },
        {
            "source": 19,
            "target": 0
        },
        {
            "source": 20,
            "target": 0
        }
    ]
}